sparkmonitor/__init__.py
sparkmonitor/kernelextension.py
sparkmonitor/listener.jar
sparkmonitor/serverextension.py
sparkmonitor/static/8a7630caadfb15dbd13cb469853ab004.gif
sparkmonitor/static/module.js
sparkmonitor/static/module.js.map
sparkmonitor/static/taskchart.js
sparkmonitor/static/taskchart.js.map
sparkmonitor/static/timeline.js
sparkmonitor/static/timeline.js.map
sparkmonitor_s-0.0.11.dist-info/METADATA
sparkmonitor_s-0.0.11.dist-info/WHEEL
sparkmonitor_s-0.0.11.dist-info/top_level.txt
sparkmonitor_s-0.0.11.dist-info/RECORD
