Metadata-Version: 2.1
Name: sparkmonitor-s
Version: 0.0.11
Summary: Spark Monitor Extension for Jupyter Notebook
Home-page: https://github.com/krishnan-r/sparkmonitor
Author: Krishnan R
Author-email: krishnanr1997@gmail.com
License: UNKNOWN
Platform: UNKNOWN
Requires-Dist: bs4
